concierge_api_client/__init__.py
concierge_api_client/auth_client.py
concierge_api_client/base_client.py
concierge_api_client/client.py
concierge_api_client/codes.py
concierge_api_client/exceptions.py
concierge_api_client/raise_error.py
concierge_api_client-0.1a2.dist-info/METADATA
concierge_api_client-0.1a2.dist-info/WHEEL
concierge_api_client-0.1a2.dist-info/RECORD
