Metadata-Version: 2.4
Name: concierge-api-client
Version: 0.1a2
Requires-Python: >=3.12
Requires-Dist: concierge-types
Requires-Dist: httpx
Requires-Dist: python-keycloak
